COPYING
README.md
guardian/__init__.py
guardian/conf.py
guardian/config/conf.cfg.sample
guardian/config/services.yaml.example
guardian/main.py
guardian/notification.py
guardian/probes/__init__.py
guardian/probes/httpGet.py
guardian/templates/email.txt
guardian/templates/report.html
guardian-0.2.1.dist-info/entry_points.txt
guardian-0.2.1.dist-info/COPYING
guardian-0.2.1.dist-info/WHEEL
guardian-0.2.1.dist-info/METADATA
guardian-0.2.1.dist-info/RECORD
