Metadata-Version: 2.1
Name: guardian
Version: 0.2.1
Summary: Monitor the status of a set of services.
Home-page: https://sr.ht/~cedric/guardian
License: AGPL-3.0-or-later
Keywords: monitoring,system,notification,report
Author: Cédric Bonhomme
Author-email: cedric@cedricbonhomme.org
Requires-Python: >=3.8,<4.0
Classifier: Development Status :: 5 - Production/Stable
Classifier: Environment :: Console
Classifier: Intended Audience :: System Administrators
Classifier: License :: OSI Approved :: GNU Affero General Public License v3 or later (AGPLv3+)
Classifier: License :: OSI Approved :: GNU General Public License v3 or later (GPLv3+)
Classifier: Operating System :: POSIX :: Linux
Classifier: Programming Language :: Python :: 3
Classifier: Programming Language :: Python :: 3.8
Classifier: Programming Language :: Python :: 3.9
Classifier: Topic :: System :: Monitoring
Requires-Dist: Jinja2 (>=2.11.3,<3.0.0)
Requires-Dist: PyYAML (>=5.4.1,<6.0.0)
Project-URL: Bug Tracker, https://todo.sr.ht/~cedric/guardian
Project-URL: Repository, https://git.sr.ht/~cedric/guardian
